WerkzeugZhongwenWendang/README.md
WerkzeugZhongwenWendang/__init__.py
WerkzeugZhongwenWendang/__main__.py
WerkzeugZhongwenWendang/file.epub
WerkzeugZhongwenWendang/index.html
WerkzeugZhongwenWendang/css/__init__.py
WerkzeugZhongwenWendang/css/annotations.css
WerkzeugZhongwenWendang/css/main.css
WerkzeugZhongwenWendang/css/normalize.css
WerkzeugZhongwenWendang/css/popup.css
WerkzeugZhongwenWendang/font/__init__.py
WerkzeugZhongwenWendang/font/fontello.eot
WerkzeugZhongwenWendang/font/fontello.svg
WerkzeugZhongwenWendang/font/fontello.ttf
WerkzeugZhongwenWendang/font/fontello.woff
WerkzeugZhongwenWendang/img/__init__.py
WerkzeugZhongwenWendang/img/annotator-glyph-sprite.png
WerkzeugZhongwenWendang/img/annotator-icon-sprite.png
WerkzeugZhongwenWendang/img/apple-touch-icon.png
WerkzeugZhongwenWendang/img/cancelfullscreen.png
WerkzeugZhongwenWendang/img/close.png
WerkzeugZhongwenWendang/img/fullscreen.png
WerkzeugZhongwenWendang/img/loader.gif
WerkzeugZhongwenWendang/img/menu-icon.png
WerkzeugZhongwenWendang/img/save.png
WerkzeugZhongwenWendang/img/saved.png
WerkzeugZhongwenWendang/img/settings-s.png
WerkzeugZhongwenWendang/img/settings.png
WerkzeugZhongwenWendang/img/star.png
WerkzeugZhongwenWendang/js/__init__.py
WerkzeugZhongwenWendang/js/epub.js
WerkzeugZhongwenWendang/js/epub.min.js
WerkzeugZhongwenWendang/js/epub.min.map
WerkzeugZhongwenWendang/js/hooks.min.js
WerkzeugZhongwenWendang/js/hooks.min.map
WerkzeugZhongwenWendang/js/reader.js
WerkzeugZhongwenWendang/js/reader.js.map
WerkzeugZhongwenWendang/js/reader.min.js
WerkzeugZhongwenWendang/js/reader.min.map
WerkzeugZhongwenWendang/js/hooks/__init__.py
WerkzeugZhongwenWendang/js/hooks/extensions/__init__.py
WerkzeugZhongwenWendang/js/hooks/extensions/highlight.js
WerkzeugZhongwenWendang/js/libs/__init__.py
WerkzeugZhongwenWendang/js/libs/jquery.min.js
WerkzeugZhongwenWendang/js/libs/localforage.min.js
WerkzeugZhongwenWendang/js/libs/screenfull.js
WerkzeugZhongwenWendang/js/libs/screenfull.min.js
werkzeug_zhongwen_wendang-2024.3.2.0.dist-info/METADATA
werkzeug_zhongwen_wendang-2024.3.2.0.dist-info/WHEEL
werkzeug_zhongwen_wendang-2024.3.2.0.dist-info/entry_points.txt
werkzeug_zhongwen_wendang-2024.3.2.0.dist-info/top_level.txt
werkzeug_zhongwen_wendang-2024.3.2.0.dist-info/RECORD
